[
    {
        "authors": "Simone Carletti",
        "built_at": "2018-02-12T00:00:00.000Z",
        "created_at": "2018-02-12T09:54:34.241Z",
        "description": "PublicSuffix can parse and decompose a domain name into top level domain, domain and subdomains.",
        "downloads_count": 3037435,
        "metadata": {},
        "number": "3.0.2",
        "summary": "Domain name parser based on the Public Suffix List.",
        "platform": "ruby",
        "rubygems_version": ">= 0",
        "ruby_version": ">= 2.1",
        "prerelease": false,
        "licenses": [
            "MIT"
        ],
        "requirements": [],
        "sha": "3a0168c33fa0b00886423a2ceb21c74199273ccd01bc250360fc8d18600bb0f4"
    },
    {
        "authors": "Simone Carletti",
        "built_at": "2017-11-08T00:00:00.000Z",
        "created_at": "2017-11-08T20:42:38.512Z",
        "description": "PublicSuffix can parse and decompose a domain name into top level domain, domain and subdomains.",
        "downloads_count": 4988570,
        "metadata": {},
        "number": "3.0.1",
        "summary": "Domain name parser based on the Public Suffix List.",
        "platform": "ruby",
        "rubygems_version": ">= 0",
        "ruby_version": ">= 2.1",
        "prerelease": false,
        "licenses": [
            "MIT"
        ],
        "requirements": [],
        "sha": "67182699cb644e66b4c68d30b5f1dd42e3dfe6c0aa0d8fd36a1e71c97c6a7f57"
    },
    {
        "authors": "Simone Carletti",
        "built_at": "2017-08-04T00:00:00.000Z",
        "created_at": "2017-08-04T13:18:28.678Z",
        "description": "PublicSuffix can parse and decompose a domain name into top level domain, domain and subdomains.",
        "downloads_count": 4743800,
        "metadata": {},
        "number": "3.0.0",
        "summary": "Domain name parser based on the Public Suffix List.",
        "platform": "ruby",
        "rubygems_version": ">= 0",
        "ruby_version": ">= 2.1",
        "prerelease": false,
        "licenses": [
            "MIT"
        ],
        "requirements": [],
        "sha": "ae48d8122866e342c09f1f643c2b88e3547562fd6df85d83926445d75f90ca6a"
    },
    {
        "authors": "Simone Carletti",
        "built_at": "2017-01-02T00:00:00.000Z",
        "created_at": "2017-01-02T17:06:24.459Z",
        "description": "PublicSuffix can parse and decompose a domain name into top level domain, domain and subdomains.",
        "downloads_count": 16274671,
        "metadata": {},
        "number": "2.0.5",
        "summary": "Domain name parser based on the Public Suffix List.",
        "platform": "ruby",
        "rubygems_version": ">= 0",
        "ruby_version": ">= 2.0",
        "prerelease": false,
        "licenses": [
            "MIT"
        ],
        "requirements": [],
        "sha": "f8488b110921532ff291af74eef70fa4e3c036141c4ef80009dcdc2b51721210"
    },
    {
        "authors": "Simone Carletti",
        "built_at": "2016-11-07T00:00:00.000Z",
        "created_at": "2016-11-07T00:08:45.525Z",
        "description": "PublicSuffix can parse and decompose a domain name into top level domain, domain and subdomains.",
        "downloads_count": 3159787,
        "metadata": {},
        "number": "2.0.4",
        "summary": "Domain name parser based on the Public Suffix List.",
        "platform": "ruby",
        "rubygems_version": ">= 0",
        "ruby_version": ">= 2.0",
        "prerelease": false,
        "licenses": [
            "MIT"
        ],
        "requirements": [],
        "sha": "1d10f21372a31e54fb3e6f5cf0040954fca4bce626c7aa97679258923c8de5c5"
    },
    {
        "authors": "Simone Carletti",
        "built_at": "2016-09-30T00:00:00.000Z",
        "created_at": "2016-09-30T08:13:12.703Z",
        "description": "PublicSuffix can parse and decompose a domain name into top level domain, domain and subdomains.",
        "downloads_count": 89256,
        "metadata": {},
        "number": "2.0.3",
        "summary": "Domain name parser based on the Public Suffix List.",
        "platform": "ruby",
        "rubygems_version": ">= 0",
        "ruby_version": ">= 2.0",
        "prerelease": false,
        "licenses": [
            "MIT"
        ],
        "requirements": [],
        "sha": "69cf11137edc0cb78b21592e9fdc34661c4774d4359e172737aa747537f75619"
    },
    {
        "authors": "Simone Carletti",
        "built_at": "2016-06-10T00:00:00.000Z",
        "created_at": "2016-06-10T07:45:24.300Z",
        "description": "PublicSuffix can parse and decompose a domain name into top level domain, domain and subdomains.",
        "downloads_count": 131899,
        "metadata": {},
        "number": "2.0.2",
        "summary": "Domain name parser based on the Public Suffix List.",
        "platform": "ruby",
        "rubygems_version": ">= 0",
        "ruby_version": ">= 2.0",
        "prerelease": false,
        "licenses": [
            "MIT"
        ],
        "requirements": [],
        "sha": "a2f9142607d625431bb6c8f6af3187727813c69fdbfc41a300dcb45f03ab011e"
    },
    {
        "authors": "Simone Carletti",
        "built_at": "2016-05-22T00:00:00.000Z",
        "created_at": "2016-05-22T08:13:06.904Z",
        "description": "PublicSuffix can parse and decompose a domain name into top level domain, domain and subdomains.",
        "downloads_count": 20441,
        "metadata": {},
        "number": "2.0.1",
        "summary": "Domain name parser based on the Public Suffix List.",
        "platform": "ruby",
        "rubygems_version": ">= 0",
        "ruby_version": ">= 2.0",
        "prerelease": false,
        "licenses": [
            "MIT"
        ],
        "requirements": [],
        "sha": "349ab4d06554994b94087f3fce3027ee4450eaab6d4acfe9721d054d1fbdd6ce"
    },
    {
        "authors": "Simone Carletti",
        "built_at": "2016-05-20T00:00:00.000Z",
        "created_at": "2016-05-20T10:45:01.439Z",
        "description": "PublicSuffix can parse and decompose a domain name into top level domain, domain and subdomains.",
        "downloads_count": 1211,
        "metadata": {},
        "number": "2.0.0",
        "summary": "Domain name parser based on the Public Suffix List.",
        "platform": "ruby",
        "rubygems_version": ">= 0",
        "ruby_version": ">= 2.0",
        "prerelease": false,
        "licenses": [
            "MIT"
        ],
        "requirements": [],
        "sha": "2adc4219ccb2ec180f2c3f898112d51499f354f884f8ee13b8bd14e14478ce9e"
    },
    {
        "authors": "Simone Carletti",
        "built_at": "2015-12-14T00:00:00.000Z",
        "created_at": "2015-12-14T12:56:02.425Z",
        "description": "PublicSuffix can parse and decompose a domain name into top level domain, domain and subdomains.",
        "downloads_count": 485632,
        "metadata": {},
        "number": "1.5.3",
        "summary": "Domain name parser based on the Public Suffix List.",
        "platform": "ruby",
        "rubygems_version": ">= 0",
        "ruby_version": ">= 2.0",
        "prerelease": false,
        "licenses": [
            "MIT"
        ],
        "requirements": [],
        "sha": "ac7814801e511a14e45938e231b656181a967d87bb437444900495513275380b"
    },
    {
        "authors": "Simone Carletti",
        "built_at": "2015-10-27T00:00:00.000Z",
        "created_at": "2015-10-27T16:52:20.344Z",
        "description": "PublicSuffix can parse and decompose a domain name into top level domain, domain and subdomains.",
        "downloads_count": 64252,
        "metadata": {},
        "number": "1.5.2",
        "summary": "Domain name parser based on the Public Suffix List.",
        "platform": "ruby",
        "rubygems_version": ">= 0",
        "ruby_version": ">= 2.0",
        "prerelease": false,
        "licenses": [
            "MIT"
        ],
        "requirements": [],
        "sha": "b5e9dc5f72cdc3d97fcdedb4eaf26f6605b321850539571ed1cde795d109994e"
    },
    {
        "authors": "Simone Carletti",
        "built_at": "2015-04-10T00:00:00.000Z",
        "created_at": "2015-04-10T11:59:46.894Z",
        "description": "PublicSuffix can parse and decompose a domain name into top level domain, domain and subdomains.",
        "downloads_count": 195755,
        "metadata": {},
        "number": "1.5.1",
        "summary": "Domain name parser based on the Public Suffix List.",
        "platform": "ruby",
        "rubygems_version": ">= 0",
        "ruby_version": ">= 2.0",
        "prerelease": false,
        "licenses": [
            "MIT"
        ],
        "requirements": [],
        "sha": "a0395cd504d57c98955293ff280c45141a203c7170e9dc6939382e3a7c8f374a"
    },
    {
        "authors": "Simone Carletti",
        "built_at": "2015-03-24T00:00:00.000Z",
        "created_at": "2015-03-24T10:12:33.337Z",
        "description": "PublicSuffix can parse and decompose a domain name into top level domain, domain and subdomains.",
        "downloads_count": 13766,
        "metadata": {},
        "number": "1.5.0",
        "summary": "Domain name parser based on the Public Suffix List.",
        "platform": "ruby",
        "rubygems_version": ">= 0",
        "ruby_version": ">= 2.0",
        "prerelease": false,
        "licenses": [
            "MIT"
        ],
        "requirements": [],
        "sha": "19c503f41e635023270147997e7509d41a5c1f22f5c3eb8fd58c44e32b7fc4b7"
    },
    {
        "authors": "Simone Carletti",
        "built_at": "2014-09-10T00:00:00.000Z",
        "created_at": "2014-09-10T08:28:54.874Z",
        "description": "PublicSuffix can parse and decompose a domain name into top level domain, domain and subdomains.",
        "downloads_count": 1224154,
        "metadata": {},
        "number": "1.4.6",
        "summary": "Domain name parser based on the Public Suffix List.",
        "platform": "ruby",
        "rubygems_version": ">= 0",
        "ruby_version": ">= 1.9.3",
        "prerelease": false,
        "licenses": [
            "MIT"
        ],
        "requirements": [],
        "sha": "20e0e795fdd5b2c602f2c0e061352c51772a32830d812653c37c56473d59aa75"
    },
    {
        "authors": "Simone Carletti",
        "built_at": "2014-08-18T00:00:00.000Z",
        "created_at": "2014-08-18T21:23:14.820Z",
        "description": "PublicSuffix can parse and decompose a domain name into top level domain, domain and subdomains.",
        "downloads_count": 16142,
        "metadata": {},
        "number": "1.4.5",
        "summary": "Domain name parser based on the Public Suffix List.",
        "platform": "ruby",
        "rubygems_version": ">= 0",
        "ruby_version": ">= 1.9.3",
        "prerelease": false,
        "licenses": [
            "MIT"
        ],
        "requirements": [],
        "sha": "be70cc38bf75bc498887ba86fb704e768377f891bdb3279861cce21d14dbea1e"
    },
    {
        "authors": "Simone Carletti",
        "built_at": "2014-06-17T00:00:00.000Z",
        "created_at": "2014-06-17T15:08:39.915Z",
        "description": "PublicSuffix can parse and decompose a domain name into top level domain, domain and subdomains.",
        "downloads_count": 29116,
        "metadata": {},
        "number": "1.4.4",
        "summary": "Domain name parser based on the Public Suffix List.",
        "platform": "ruby",
        "rubygems_version": ">= 0",
        "ruby_version": ">= 1.9.3",
        "prerelease": false,
        "licenses": [
            "MIT"
        ],
        "requirements": [],
        "sha": "1ff9d9fbf07d2a1729831126497877d864564d304c0038608a52522ca049c461"
    },
    {
        "authors": "Simone Carletti",
        "built_at": "2014-06-12T00:00:00.000Z",
        "created_at": "2014-06-12T07:22:54.816Z",
        "description": "PublicSuffix can parse and decompose a domain name into top level domain, domain and subdomains.",
        "downloads_count": 25520,
        "metadata": {},
        "number": "1.4.3",
        "summary": "Domain name parser based on the Public Suffix List.",
        "platform": "ruby",
        "rubygems_version": ">= 0",
        "ruby_version": ">= 1.9.3",
        "prerelease": false,
        "licenses": [
            "MIT"
        ],
        "requirements": [],
        "sha": "9723562250f4be06da41e6c02df8114706687648023621e46e3c2e1ba11406ef"
    },
    {
        "authors": "Simone Carletti",
        "built_at": "2014-03-10T00:00:00.000Z",
        "created_at": "2014-03-10T13:41:17.832Z",
        "description": "PublicSuffix can parse and decompose a domain name into top level domain, domain and subdomains.",
        "downloads_count": 37776,
        "metadata": {},
        "number": "1.4.2",
        "summary": "Domain name parser based on the Public Suffix List.",
        "platform": "ruby",
        "rubygems_version": ">= 0",
        "ruby_version": null,
        "prerelease": false,
        "licenses": [
            "MIT"
        ],
        "requirements": [],
        "sha": "8d1324c043d43547e3f7ad3108637562442eda797f1d3ec86f289e0e43b70bbd"
    },
    {
        "authors": "Simone Carletti",
        "built_at": "2014-03-07T00:00:00.000Z",
        "created_at": "2014-03-07T15:10:55.893Z",
        "description": "PublicSuffix can parse and decompose a domain name into top level domain, domain and subdomains.",
        "downloads_count": 1302,
        "metadata": {},
        "number": "1.4.1",
        "summary": "Domain name parser based on the Public Suffix List.",
        "platform": "ruby",
        "rubygems_version": ">= 0",
        "ruby_version": null,
        "prerelease": false,
        "licenses": [
            "MIT"
        ],
        "requirements": [],
        "sha": "e9cbab386ca7011bdce112c4b82142ad90ad13bb561c69d23dbd81429ce0c6b1"
    },
    {
        "authors": "Simone Carletti",
        "built_at": "2014-02-01T00:00:00.000Z",
        "created_at": "2014-02-01T14:09:19.988Z",
        "description": "PublicSuffix can parse and decompose a domain name into top level domain, domain and subdomains.",
        "downloads_count": 6544,
        "metadata": {},
        "number": "1.4.0",
        "summary": "Domain name parser based on the Public Suffix List.",
        "platform": "ruby",
        "rubygems_version": ">= 0",
        "ruby_version": null,
        "prerelease": false,
        "licenses": [
            "MIT"
        ],
        "requirements": [],
        "sha": "5bc57bda7c408e3e003fdb9bb592e46d8ec59cc4f3b0374d94c8cc79abf97ed5"
    },
    {
        "authors": "Simone Carletti",
        "built_at": "2013-12-01T00:00:00.000Z",
        "created_at": "2013-12-01T15:06:45.905Z",
        "description": "PublicSuffix can parse and decompose a domain name into top level domain, domain and subdomains.",
        "downloads_count": 52318,
        "metadata": {},
        "number": "1.3.3",
        "summary": "Domain name parser based in the Public Suffix List.",
        "platform": "ruby",
        "rubygems_version": ">= 0",
        "ruby_version": null,
        "prerelease": false,
        "licenses": [
            "MIT"
        ],
        "requirements": [],
        "sha": "2b5c490586ee29c96ffff2b35bc06adb4810fa27e2d1c7adfcfed159613782c1"
    },
    {
        "authors": "Simone Carletti",
        "built_at": "2013-11-11T00:00:00.000Z",
        "created_at": "2013-11-11T14:15:09.715Z",
        "description": "PublicSuffix can parse and decompose a domain name into top level domain, domain and subdomains.",
        "downloads_count": 10458,
        "metadata": {},
        "number": "1.3.2",
        "summary": "Domain name parser based in the Public Suffix List.",
        "platform": "ruby",
        "rubygems_version": ">= 0",
        "ruby_version": null,
        "prerelease": false,
        "licenses": [],
        "requirements": [],
        "sha": "19c6e34ce705b1d10f37d9dee52f3481a1d6a2db72ea61e1fb47309eb9169747"
    },
    {
        "authors": "Simone Carletti",
        "built_at": "2013-08-09T00:00:00.000Z",
        "created_at": "2013-08-09T02:43:29.333Z",
        "description": "PublicSuffix can parse and decompose a domain name into top level domain, domain and subdomains.",
        "downloads_count": 62022,
        "metadata": {},
        "number": "1.3.1",
        "summary": "Domain name parser based in the Public Suffix List.",
        "platform": "ruby",
        "rubygems_version": ">= 0",
        "ruby_version": null,
        "prerelease": false,
        "licenses": [],
        "requirements": [],
        "sha": "a6feb81f3ff006f10f1d31d4276574c7aea83b0d28471c1defd5267903bbc68d"
    },
    {
        "authors": "Simone Carletti",
        "built_at": "2013-04-03T00:00:00.000Z",
        "created_at": "2013-04-03T13:34:31.509Z",
        "description": "PublicSuffix can parse and decompose a domain name into top level domain, domain and subdomains.",
        "downloads_count": 69672,
        "metadata": {},
        "number": "1.3.0",
        "summary": "Domain name parser based in the Public Suffix List.",
        "platform": "ruby",
        "rubygems_version": ">= 0",
        "ruby_version": null,
        "prerelease": false,
        "licenses": [],
        "requirements": null,
        "sha": "da94da1785f5ffa29bbb52de7dbe488d109c403f5db525846f157261a9d07c69"
    },
    {
        "authors": "Simone Carletti",
        "built_at": "2013-03-26T00:00:00.000Z",
        "created_at": "2013-03-26T14:11:55.084Z",
        "description": "PublicSuffix can parse and decompose a domain name into top level domain, domain and subdomains.",
        "downloads_count": 18531,
        "metadata": {},
        "number": "1.2.1",
        "summary": "Domain name parser based in the Public Suffix List.",
        "platform": "ruby",
        "rubygems_version": ">= 0",
        "ruby_version": null,
        "prerelease": false,
        "licenses": [],
        "requirements": null,
        "sha": "ea04246416a45fd56560a008bf623af933fc343672f5cdcfe32434d3c7484ac9"
    },
    {
        "authors": "Simone Carletti",
        "built_at": "2012-12-24T00:00:00.000Z",
        "created_at": "2012-12-24T22:48:09.779Z",
        "description": "PublicSuffix can parse and decompose a domain name into top level domain, domain and subdomains.",
        "downloads_count": 17313,
        "metadata": {},
        "number": "1.2.0",
        "summary": "Domain name parser based in the Public Suffix List.",
        "platform": "ruby",
        "rubygems_version": ">= 0",
        "ruby_version": null,
        "prerelease": false,
        "licenses": [],
        "requirements": null,
        "sha": "fd15ad6b2a9e1dfb4cd30596745d4bd5a08c2250fa74a85f730a1a87678f7347"
    },
    {
        "authors": "Simone Carletti",
        "built_at": "2012-09-17T00:00:00.000Z",
        "created_at": "2012-09-17T13:23:51.619Z",
        "description": "PublicSuffix can parse and decompose a domain name into top level domain, domain and subdomains.",
        "downloads_count": 66699,
        "metadata": {},
        "number": "1.1.3",
        "summary": "Domain name parser based in the Public Suffix List.",
        "platform": "ruby",
        "rubygems_version": ">= 0",
        "ruby_version": null,
        "prerelease": false,
        "licenses": null,
        "requirements": null,
        "sha": "33c0b9f8a2896c12d8b7c1ff6606711e8088cfd9ef0de3b533e5221482cb961d"
    },
    {
        "authors": "Simone Carletti",
        "built_at": "2012-09-03T00:00:00.000Z",
        "created_at": "2012-09-03T21:21:02.134Z",
        "description": "PublicSuffix can parse and decompose a domain name into top level domain, domain and subdomains.",
        "downloads_count": 2357,
        "metadata": {},
        "number": "1.1.2",
        "summary": "Domain name parser based in the Public Suffix List.",
        "platform": "ruby",
        "rubygems_version": ">= 0",
        "ruby_version": null,
        "prerelease": false,
        "licenses": null,
        "requirements": null,
        "sha": "b8ac54807a4700a186a7e3ca05e5c32ee2a78fc72396a7b1746315e0b09338e2"
    },
    {
        "authors": "Simone Carletti",
        "built_at": "2012-06-26T00:00:00.000Z",
        "created_at": "2012-06-26T13:35:57.425Z",
        "description": "PublicSuffix can parse and decompose a domain name into top level domain, domain and subdomains.",
        "downloads_count": 10876,
        "metadata": {},
        "number": "1.1.1",
        "summary": "Domain name parser based in the Public Suffix List.",
        "platform": "ruby",
        "rubygems_version": ">= 0",
        "ruby_version": null,
        "prerelease": false,
        "licenses": null,
        "requirements": null,
        "sha": "92f6256ac3fb0ad675d48c981c1bbee1c4c058f893f8186565760ae4b46da9f9"
    },
    {
        "authors": "Simone Carletti",
        "built_at": "2012-03-16T00:00:00.000Z",
        "created_at": "2012-03-16T13:29:51.076Z",
        "description": "PublicSuffix can parse and decompose a domain name into top level domain, domain and subdomains.",
        "downloads_count": 8053,
        "metadata": {},
        "number": "1.1.0",
        "summary": "Domain name parser based in the Public Suffix List.",
        "platform": "ruby",
        "rubygems_version": ">= 0",
        "ruby_version": null,
        "prerelease": false,
        "licenses": null,
        "requirements": null,
        "sha": "029895daab941726aaa91050a1ac77040161b0ea38cac4f5df0954a047d578b1"
    },
    {
        "authors": "Simone Carletti",
        "built_at": "2011-12-24T00:00:00.000Z",
        "created_at": "2011-12-24T20:43:38.845Z",
        "description": "PublicSuffix can parse and decompose a domain name into top level domain, domain and subdomains.",
        "downloads_count": 9027,
        "metadata": {},
        "number": "1.0.0",
        "summary": "Domain name parser based in the Public Suffix List.",
        "platform": "ruby",
        "rubygems_version": ">= 0",
        "ruby_version": null,
        "prerelease": false,
        "licenses": null,
        "requirements": null,
        "sha": "0a1f01ca7fd41972d2cd69e45dfa4f936d98b7fd5ac9a7ee0258d3427810dc26"
    },
    {
        "authors": "Simone Carletti",
        "built_at": "2011-12-23T00:00:00.000Z",
        "created_at": "2011-12-23T19:23:25.777Z",
        "description": "PublicSuffix can parse and decompose a domain name into top level domain, domain and subdomains.",
        "downloads_count": 1071,
        "metadata": {},
        "number": "1.0.0.rc1",
        "summary": "Domain name parser based in the Public Suffix List.",
        "platform": "ruby",
        "rubygems_version": "> 1.3.1",
        "ruby_version": null,
        "prerelease": true,
        "licenses": null,
        "requirements": null,
        "sha": "926d998c09da25dc6c18504f238d4443c65c8a58209ba4280e4fd64fe1f7a2a5"
    }
]
