{
  "_attachments": {},
  "_id": "npm-package-json-lint",
  "_rev": "142-abc1234567890",
  "bugs": {
    "url": "https://github.com/ericcornelissen/npm-package-json-lint/issues"
  },
  "contributors": [
    {
      "email": "eric@example.com",
      "name": "Eric Cornelissen"
    }
  ],
  "description": "Configurable npm package.json linter",
  "dist-tags": {
    "latest": "10.0.0"
  },
  "homepage": "https://github.com/ericcornelissen/npm-package-json-lint",
  "keywords": [
    "lint",
    "npm",
    "package.json"
  ],
  "license": "MIT",
  "maintainers": [
    {
      "email": "github-actions@github.com",
      "name": "GitHub Actions"
    }
  ],
  "name": "npm-package-json-lint",
  "readme": "# npm-package-json-lint\n\nA utility for linting npm package.json files.\n",
  "readmeFilename": "README.md",
  "repository": {
    "type": "git",
    "url": "https://github.com/ericcornelissen/npm-package-json-lint"
  },
  "time": {
    "created": "2020-01-01T00:00:00.000Z",
    "modified": "2024-01-02T00:00:00.000Z",
    "9.0.0": "2024-01-01T00:00:00.000Z",
    "10.0.0": "2024-01-02T00:00:00.000Z"
  },
  "versions": {
    "9.0.0": {
      "_from": ".",
      "_id": "npm-package-json-lint@9.0.0",
      "_npmUser": {
        "email": "eric@example.com",
        "name": "oldmaintainer"
      },
      "_npmVersion": "11.10.0",
      "_shasum": "8f14e45fceea167a5a36dedd4bea2543fba3442a",
      "bugs": {
        "url": "https://github.com/ericcornelissen/npm-package-json-lint/issues"
      },
      "description": "Configurable npm package.json linter",
      "dist": {
        "shasum": "8f14e45fceea167a5a36dedd4bea2543fba3442a",
        "tarball": "https://registry.npmjs.org/npm-package-json-lint/-/npm-package-json-lint-9.0.0.tgz"
      },
      "engines": {
        "node": ">=14.0.0"
      },
      "homepage": "https://github.com/ericcornelissen/npm-package-json-lint",
      "keywords": [
        "lint",
        "npm",
        "package.json"
      ],
      "license": "MIT",
      "main": "dist/index.js",
      "name": "npm-package-json-lint",
      "repository": {
        "type": "git",
        "url": "https://github.com/ericcornelissen/npm-package-json-lint"
      },
      "version": "9.0.0"
    },
    "10.0.0": {
      "_from": ".",
      "_id": "npm-package-json-lint@10.0.0",
      "_npmUser": {
        "email": "github-actions@github.com",
        "name": "GitHub Actions"
      },
      "_npmVersion": "11.11.0",
      "_shasum": "df3c6c4ce8db6c0f5f5b92b0c1c1c0c0c0c0c0c0",
      "bugs": {
        "url": "https://github.com/ericcornelissen/npm-package-json-lint/issues"
      },
      "description": "Configurable npm package.json linter",
      "dist": {
        "shasum": "df3c6c4ce8db6c0f5f5b92b0c1c1c0c0c0c0c0c0",
        "tarball": "https://registry.npmjs.org/npm-package-json-lint/-/npm-package-json-lint-10.0.0.tgz"
      },
      "engines": {
        "node": ">=14.0.0"
      },
      "homepage": "https://github.com/ericcornelissen/npm-package-json-lint",
      "keywords": [
        "lint",
        "npm",
        "package.json"
      ],
      "license": "MIT",
      "main": "dist/index.js",
      "name": "npm-package-json-lint",
      "repository": {
        "type": "git",
        "url": "https://github.com/ericcornelissen/npm-package-json-lint"
      },
      "version": "10.0.0"
    }
  }
}
