{
    "info": {
        "maintainer": null,
        "docs_url": "http://pythonhosted.org/psycopg2/",
        "requires_python": null,
        "maintainer_email": null,
        "cheesecake_code_kwalitee_id": null,
        "keywords": null,
        "package_url": "http://pypi.python.org/pypi/psycopg2",
        "author": "Federico Di Gregorio",
        "author_email": "fog@initd.org",
        "download_url": "http://initd.org/psycopg/tarballs/PSYCOPG-2-6/psycopg2-2.6.2.tar.gz",
        "platform": "any",
        "version": "2.6.2",
        "cheesecake_documentation_id": null,
        "_pypi_hidden": false,
        "description": "Psycopg is the most popular PostgreSQL database adapter for the Python\nprogramming language.  Its main features are the complete implementation of\nthe Python DB API 2.0 specification and the thread safety (several threads can\nshare the same connection).  It was designed for heavily multi-threaded\napplications that create and destroy lots of cursors and make a large number\nof concurrent \"INSERT\"s or \"UPDATE\"s.\n\nPsycopg 2 is mostly implemented in C as a libpq wrapper, resulting in being\nboth efficient and secure.  It features client-side and server-side cursors,\nasynchronous communication and notifications, \"COPY TO/COPY FROM\" support.\nMany Python types are supported out-of-the-box and adapted to matching\nPostgreSQL data types; adaptation can be extended and customized thanks to a\nflexible objects adaptation system.\n\nPsycopg 2 is both Unicode and Python 3 friendly.\n\n\nDocumentation\n-------------\n\nDocumentation is included in the 'doc' directory and is `available online`__.\n\n.. __: http://initd.org/psycopg/docs/\n\n\nInstallation\n------------\n\nIf all the dependencies are met (i.e. you have the Python and libpq\ndevelopment packages installed in your system) the standard::\n\n    python setup.py build\n    sudo python setup.py install\n\nshould work no problem.  In case you have any problem check the 'install' and\nthe 'faq' documents in the docs or online__.\n\n.. __: http://initd.org/psycopg/docs/install.html\n\nFor any other resource (source code repository, bug tracker, mailing list)\nplease check the `project homepage`__.\n\n.. __: http://initd.org/psycopg/",
        "release_url": "http://pypi.python.org/pypi/psycopg2/2.6.2",
        "downloads": {
            "last_month": 0,
            "last_week": 0,
            "last_day": 0
        },
        "_pypi_ordering": 33,
        "classifiers": [
            "Development Status :: 5 - Production/Stable",
            "Intended Audience :: Developers",
            "License :: OSI Approved :: GNU Library or Lesser General Public License (LGPL)",
            "License :: OSI Approved :: Zope Public License",
            "Operating System :: Microsoft :: Windows",
            "Operating System :: Unix",
            "Programming Language :: C",
            "Programming Language :: Python",
            "Programming Language :: Python :: 2.5",
            "Programming Language :: Python :: 2.6",
            "Programming Language :: Python :: 2.7",
            "Programming Language :: Python :: 3",
            "Programming Language :: Python :: 3.1",
            "Programming Language :: Python :: 3.2",
            "Programming Language :: Python :: 3.3",
            "Programming Language :: Python :: 3.4",
            "Programming Language :: Python :: 3.5",
            "Programming Language :: SQL",
            "Topic :: Database",
            "Topic :: Database :: Front-Ends",
            "Topic :: Software Development",
            "Topic :: Software Development :: Libraries :: Python Modules"
        ],
        "name": "psycopg2",
        "bugtrack_url": null,
        "license": "LGPL with exceptions or ZPL",
        "summary": "psycopg2 - Python-PostgreSQL Database Adapter",
        "home_page": "http://initd.org/psycopg/",
        "cheesecake_installability_id": null
    },
    "releases": {
        "2.0.7": [],
        "2.0.6": [],
        "2.0.4": [],
        "2.0.3": [],
        "2.0.2": [],
        "2.0.5.1": [],
        "2.0.8": [],
        "2.6": [
            {
                "has_sig": true,
                "upload_time": "2015-02-09T10:02:22",
                "comment_text": "",
                "python_version": "source",
                "url": "https://pypi.python.org/packages/dd/c7/9016ff8ff69da269b1848276eebfb264af5badf6b38caad805426771f04d/psycopg2-2.6.tar.gz",
                "md5_digest": "fbbb039a8765d561a1c04969bbae7c74",
                "downloads": 1787225,
                "filename": "psycopg2-2.6.tar.gz",
                "packagetype": "sdist",
                "path": "dd/c7/9016ff8ff69da269b1848276eebfb264af5badf6b38caad805426771f04d/psycopg2-2.6.tar.gz",
                "size": 367972
            }
        ],
        "2.2.1": [
            {
                "has_sig": false,
                "upload_time": "2010-10-19T15:42:13",
                "comment_text": "",
                "python_version": "source",
                "url": "https://pypi.python.org/packages/de/c4/fdfb801035bd7da9e1ce98169d48ca2d6dee5b4361e349afbba40b3d7a5d/psycopg2-2.2.1.tar.gz",
                "md5_digest": "70b50773aefe5fb371ff4a018382012f",
                "downloads": 44315,
                "filename": "psycopg2-2.2.1.tar.gz",
                "packagetype": "sdist",
                "path": "de/c4/fdfb801035bd7da9e1ce98169d48ca2d6dee5b4361e349afbba40b3d7a5d/psycopg2-2.2.1.tar.gz",
                "size": 529408
            }
        ],
        "2.2.0": [
            {
                "has_sig": false,
                "upload_time": "2010-10-19T15:41:50",
                "comment_text": "",
                "python_version": "source",
                "url": "https://pypi.python.org/packages/32/0c/2f4da04ae2a66d71eff37f19fce67506ad28f887851cd1c1cca35ba08b36/psycopg2-2.2.0.tar.gz",
                "md5_digest": "4a69436dc8efbfe2859ae3aeed85d03e",
                "downloads": 5166,
                "filename": "psycopg2-2.2.0.tar.gz",
                "packagetype": "sdist",
                "path": "32/0c/2f4da04ae2a66d71eff37f19fce67506ad28f887851cd1c1cca35ba08b36/psycopg2-2.2.0.tar.gz",
                "size": 528718
            }
        ],
        "2.2.2": [
            {
                "has_sig": false,
                "upload_time": "2010-09-09T10:53:08",
                "comment_text": "",
                "python_version": "source",
                "url": "https://pypi.python.org/packages/63/3e/a4a35761eb4595fff89e63347b4f8e79c2095782fa5bc016a6dfb18b21ac/psycopg2-2.2.2.tar.gz",
                "md5_digest": "571af2ad9dfeb522ee5f8553278a4c38",
                "downloads": 27853,
                "filename": "psycopg2-2.2.2.tar.gz",
                "packagetype": "sdist",
                "path": "63/3e/a4a35761eb4595fff89e63347b4f8e79c2095782fa5bc016a6dfb18b21ac/psycopg2-2.2.2.tar.gz",
                "size": 530021
            }
        ],
        "2.5.4": [
            {
                "has_sig": true,
                "upload_time": "2014-08-30T18:04:42",
                "comment_text": "",
                "python_version": "source",
                "url": "https://pypi.python.org/packages/63/c3/802668cb3cfc2880c2a8364623e7105a0257724a2612bb66ec733aaddb8c/psycopg2-2.5.4.tar.gz",
                "md5_digest": "25216543a707eb33fd83aa8efb6e3f26",
                "downloads": 1866067,
                "filename": "psycopg2-2.5.4.tar.gz",
                "packagetype": "sdist",
                "path": "63/c3/802668cb3cfc2880c2a8364623e7105a0257724a2612bb66ec733aaddb8c/psycopg2-2.5.4.tar.gz",
                "size": 682578
            }
        ],
        "2.5": [
            {
                "has_sig": true,
                "upload_time": "2013-04-07T18:18:13",
                "comment_text": "",
                "python_version": "source",
                "url": "https://pypi.python.org/packages/84/7e/7256298bf7064238e63b9380cf424f776a4d2a87e387c9a9bd1bc5ea0fbc/psycopg2-2.5.tar.gz",
                "md5_digest": "facd82faa067e99b80146a0ee2f842f6",
                "downloads": 239430,
                "filename": "psycopg2-2.5.tar.gz",
                "packagetype": "sdist",
                "path": "84/7e/7256298bf7064238e63b9380cf424f776a4d2a87e387c9a9bd1bc5ea0fbc/psycopg2-2.5.tar.gz",
                "size": 703558
            }
        ],
        "2.4": [
            {
                "has_sig": false,
                "upload_time": "2011-02-27T16:52:11",
                "comment_text": "",
                "python_version": "source",
                "url": "https://pypi.python.org/packages/ce/2d/e9e65ee32ef2657028109bd5a1c1ece97e409ebf790b6ee286aae2c6b890/psycopg2-2.4.tar.gz",
                "md5_digest": "24f4368e2cfdc1a2b03282ddda814160",
                "downloads": 78219,
                "filename": "psycopg2-2.4.tar.gz",
                "packagetype": "sdist",
                "path": "ce/2d/e9e65ee32ef2657028109bd5a1c1ece97e409ebf790b6ee286aae2c6b890/psycopg2-2.4.tar.gz",
                "size": 607925
            }
        ],
        "2.4.6": [
            {
                "has_sig": true,
                "upload_time": "2012-12-12T10:51:33",
                "comment_text": "",
                "python_version": "source",
                "url": "https://pypi.python.org/packages/59/aa/4d74a5dc32a89d622c1fa896a86683b488ef255f06d4b27231e12e6076f7/psycopg2-2.4.6.tar.gz",
                "md5_digest": "79d7f05e67bf70a0ecc6e9103ccece5f",
                "downloads": 464523,
                "filename": "psycopg2-2.4.6.tar.gz",
                "packagetype": "sdist",
                "path": "59/aa/4d74a5dc32a89d622c1fa896a86683b488ef255f06d4b27231e12e6076f7/psycopg2-2.4.6.tar.gz",
                "size": 667783
            }
        ],
        "2.5.1": [
            {
                "has_sig": true,
                "upload_time": "2013-06-23T19:24:08",
                "comment_text": "",
                "python_version": "source",
                "url": "https://pypi.python.org/packages/22/09/63d5da7375c267e208bbadf56b51699d85cb7b3a9096817eeea500a27b3b/psycopg2-2.5.1.tar.gz",
                "md5_digest": "1b433f83d50d1bc61e09026e906d84c7",
                "downloads": 1488696,
                "filename": "psycopg2-2.5.1.tar.gz",
                "packagetype": "sdist",
                "path": "22/09/63d5da7375c267e208bbadf56b51699d85cb7b3a9096817eeea500a27b3b/psycopg2-2.5.1.tar.gz",
                "size": 684504
            }
        ],
        "2.3.0": [
            {
                "has_sig": false,
                "upload_time": "2010-12-02T00:53:24",
                "comment_text": "",
                "python_version": "source",
                "url": "https://pypi.python.org/packages/68/0a/459df8dcbcc118ca435e9567abceaab919706908d52139e503f6396c4935/psycopg2-2.3.0.tar.gz",
                "md5_digest": "0b52101b47f1e73001c6412d9a476222",
                "downloads": 6552,
                "filename": "psycopg2-2.3.0.tar.gz",
                "packagetype": "sdist",
                "path": "68/0a/459df8dcbcc118ca435e9567abceaab919706908d52139e503f6396c4935/psycopg2-2.3.0.tar.gz",
                "size": 588979
            }
        ],
        "2.3.1": [
            {
                "has_sig": false,
                "upload_time": "2010-12-04T22:24:29",
                "comment_text": "",
                "python_version": "source",
                "url": "https://pypi.python.org/packages/cd/7c/6acf5aacd347f3dc1398eca0e2123c35a48efb07617d4d9578e9cd79a1a7/psycopg2-2.3.1.tar.gz",
                "md5_digest": "15d1c7f821f3a0306955d6cde3e762af",
                "downloads": 20602,
                "filename": "psycopg2-2.3.1.tar.gz",
                "packagetype": "sdist",
                "path": "cd/7c/6acf5aacd347f3dc1398eca0e2123c35a48efb07617d4d9578e9cd79a1a7/psycopg2-2.3.1.tar.gz",
                "size": 567191
            }
        ],
        "2.3.2": [
            {
                "has_sig": false,
                "upload_time": "2011-02-18T12:33:34",
                "comment_text": "",
                "python_version": "source",
                "url": "https://pypi.python.org/packages/50/48/32927cbc99633613704950be5013fc144aa0f451a5e0616635a934d94a62/psycopg2-2.3.2.tar.gz",
                "md5_digest": "11e8021a4fda49faa15495f8bea65f4d",
                "downloads": 11128,
                "filename": "psycopg2-2.3.2.tar.gz",
                "packagetype": "sdist",
                "path": "50/48/32927cbc99633613704950be5013fc144aa0f451a5e0616635a934d94a62/psycopg2-2.3.2.tar.gz",
                "size": 568029
            }
        ],
        "2.4.3": [
            {
                "has_sig": false,
                "upload_time": "2011-12-12T12:15:35",
                "comment_text": "",
                "python_version": "source",
                "url": "https://pypi.python.org/packages/1e/71/8929172068cbc3d3c7288bf888a7df5862a28d67ed61ad9b4c7aa5cf8be8/psycopg2-2.4.3.tar.gz",
                "md5_digest": "5f67ca0c8b6c1ac5c4afd82811e0facc",
                "downloads": 16990,
                "filename": "psycopg2-2.4.3.tar.gz",
                "packagetype": "sdist",
                "path": "1e/71/8929172068cbc3d3c7288bf888a7df5862a28d67ed61ad9b4c7aa5cf8be8/psycopg2-2.4.3.tar.gz",
                "size": 647008
            }
        ],
        "2.4.2": [
            {
                "has_sig": false,
                "upload_time": "2011-06-17T15:15:38",
                "comment_text": "",
                "python_version": "source",
                "url": "https://pypi.python.org/packages/70/91/345f8eb32dc333331510e1adad858f7a1478d3a1e4aae05ee188985c6b17/psycopg2-2.4.2.tar.gz",
                "md5_digest": "58cfd294d28b7e8ef059d72085d71ac2",
                "downloads": 105108,
                "filename": "psycopg2-2.4.2.tar.gz",
                "packagetype": "sdist",
                "path": "70/91/345f8eb32dc333331510e1adad858f7a1478d3a1e4aae05ee188985c6b17/psycopg2-2.4.2.tar.gz",
                "size": 667192
            }
        ],
        "2.4.1": [
            {
                "has_sig": false,
                "upload_time": "2011-05-11T12:56:53",
                "comment_text": "",
                "python_version": "source",
                "url": "https://pypi.python.org/packages/82/f8/6c80beb1b58f01f52dcdfa52bc1668caa4e3fc4927e9230edc40afa98c05/psycopg2-2.4.1.tar.gz",
                "md5_digest": "4e79c822ab75dd89d931ee627c66032f",
                "downloads": 219576,
                "filename": "psycopg2-2.4.1.tar.gz",
                "packagetype": "sdist",
                "path": "82/f8/6c80beb1b58f01f52dcdfa52bc1668caa4e3fc4927e9230edc40afa98c05/psycopg2-2.4.1.tar.gz",
                "size": 398200
            }
        ],
        "2.5.5": [
            {
                "has_sig": true,
                "upload_time": "2015-02-09T09:59:31",
                "comment_text": "",
                "python_version": "source",
                "url": "https://pypi.python.org/packages/9b/60/f4c79e73a69ded145880bcf4f98eeed741af12c62c5ddc89b754602b1807/psycopg2-2.5.5.tar.gz",
                "md5_digest": "1404a6cc0108eed5d7dd0c1dc9a1c074",
                "downloads": 64048,
                "filename": "psycopg2-2.5.5.tar.gz",
                "packagetype": "sdist",
                "path": "9b/60/f4c79e73a69ded145880bcf4f98eeed741af12c62c5ddc89b754602b1807/psycopg2-2.5.5.tar.gz",
                "size": 779757
            }
        ],
        "2.5.2": [
            {
                "has_sig": true,
                "upload_time": "2014-01-07T12:25:11",
                "comment_text": "",
                "python_version": "source",
                "url": "https://pypi.python.org/packages/c3/f3/5519551f02ae70fc51f4e608e7b44d59a408fe3264fec4afeea37b8ea317/psycopg2-2.5.2.tar.gz",
                "md5_digest": "53d81793fbab8fee6e732a0425d50047",
                "downloads": 1030601,
                "filename": "psycopg2-2.5.2.tar.gz",
                "packagetype": "sdist",
                "path": "c3/f3/5519551f02ae70fc51f4e608e7b44d59a408fe3264fec4afeea37b8ea317/psycopg2-2.5.2.tar.gz",
                "size": 685762
            }
        ],
        "2.5.3": [
            {
                "has_sig": true,
                "upload_time": "2014-05-13T16:51:38",
                "comment_text": "",
                "python_version": "source",
                "url": "https://pypi.python.org/packages/22/fa/5ddcafc7387c1534c59eb3ffcdb9ab2af106fd3b104e6df191b6c55718af/psycopg2-2.5.3.tar.gz",
                "md5_digest": "09dcec70f623a9ef774f1aef75690995",
                "downloads": 1114861,
                "filename": "psycopg2-2.5.3.tar.gz",
                "packagetype": "sdist",
                "path": "22/fa/5ddcafc7387c1534c59eb3ffcdb9ab2af106fd3b104e6df191b6c55718af/psycopg2-2.5.3.tar.gz",
                "size": 690689
            }
        ],
        "2.4.5": [
            {
                "has_sig": true,
                "upload_time": "2012-03-29T11:42:27",
                "comment_text": "",
                "python_version": "source",
                "url": "https://pypi.python.org/packages/36/77/894a5dd9f3f55cfc85682d3e6473ee5103d8d418b95baf4019fad3ffa026/psycopg2-2.4.5.tar.gz",
                "md5_digest": "075e4df465e9a863f288d5bdf6e6887e",
                "downloads": 7212996,
                "filename": "psycopg2-2.4.5.tar.gz",
                "packagetype": "sdist",
                "path": "36/77/894a5dd9f3f55cfc85682d3e6473ee5103d8d418b95baf4019fad3ffa026/psycopg2-2.4.5.tar.gz",
                "size": 719343
            }
        ],
        "2.4.4": [
            {
                "has_sig": false,
                "upload_time": "2011-12-19T13:38:39",
                "comment_text": "",
                "python_version": "source",
                "url": "https://pypi.python.org/packages/6f/91/890c6f954e2d09d26b266a24468570c6227de61ac6f64926c48000db0a6e/psycopg2-2.4.4.tar.gz",
                "md5_digest": "639e014ea9ce3aa3306724f12d16d79b",
                "downloads": 102479,
                "filename": "psycopg2-2.4.4.tar.gz",
                "packagetype": "sdist",
                "path": "6f/91/890c6f954e2d09d26b266a24468570c6227de61ac6f64926c48000db0a6e/psycopg2-2.4.4.tar.gz",
                "size": 648954
            }
        ],
        "2.6.1": [
            {
                "has_sig": false,
                "upload_time": "2015-11-06T21:07:04",
                "comment_text": "",
                "python_version": "cp26",
                "url": "https://pypi.python.org/packages/47/ed/5bd02bf1a7f78823f8a708beb3656f7c3ad935fb013c7063ff5f67848a52/psycopg2-2.6.1-cp26-none-win32.whl",
                "md5_digest": "a849b57608acf6ae26db67cf6b7667b5",
                "downloads": 1109,
                "filename": "psycopg2-2.6.1-cp26-none-win32.whl",
                "packagetype": "bdist_wheel",
                "path": "47/ed/5bd02bf1a7f78823f8a708beb3656f7c3ad935fb013c7063ff5f67848a52/psycopg2-2.6.1-cp26-none-win32.whl",
                "size": 814523
            },
            {
                "has_sig": false,
                "upload_time": "2015-11-06T21:07:14",
                "comment_text": "",
                "python_version": "cp26",
                "url": "https://pypi.python.org/packages/2e/40/8ab9a8d99b7abd2b95858872fee6894a3eb4fc361692abc02e94091aa54b/psycopg2-2.6.1-cp26-none-win_amd64.whl",
                "md5_digest": "66fda625af6267f020abc06a66afe75b",
                "downloads": 921,
                "filename": "psycopg2-2.6.1-cp26-none-win_amd64.whl",
                "packagetype": "bdist_wheel",
                "path": "2e/40/8ab9a8d99b7abd2b95858872fee6894a3eb4fc361692abc02e94091aa54b/psycopg2-2.6.1-cp26-none-win_amd64.whl",
                "size": 1162332
            },
            {
                "has_sig": false,
                "upload_time": "2015-11-06T21:07:21",
                "comment_text": "",
                "python_version": "cp27",
                "url": "https://pypi.python.org/packages/1f/84/a2fffb87348bc688d70bcdc24e761b06f48d958e1c1adfc3fa9eb3f4379c/psycopg2-2.6.1-cp27-none-win32.whl",
                "md5_digest": "089acf7f1a8349c6308106bec896c762",
                "downloads": 13199,
                "filename": "psycopg2-2.6.1-cp27-none-win32.whl",
                "packagetype": "bdist_wheel",
                "path": "1f/84/a2fffb87348bc688d70bcdc24e761b06f48d958e1c1adfc3fa9eb3f4379c/psycopg2-2.6.1-cp27-none-win32.whl",
                "size": 814322
            },
            {
                "has_sig": false,
                "upload_time": "2015-11-06T21:07:28",
                "comment_text": "",
                "python_version": "cp27",
                "url": "https://pypi.python.org/packages/b5/37/b6e759f1f6a0fd32ad0e1b2576bf94cfa252710cad66e155f47fc04ba744/psycopg2-2.6.1-cp27-none-win_amd64.whl",
                "md5_digest": "a8d7808e7c67e5bc0b6088a56045d2d2",
                "downloads": 5864,
                "filename": "psycopg2-2.6.1-cp27-none-win_amd64.whl",
                "packagetype": "bdist_wheel",
                "path": "b5/37/b6e759f1f6a0fd32ad0e1b2576bf94cfa252710cad66e155f47fc04ba744/psycopg2-2.6.1-cp27-none-win_amd64.whl",
                "size": 1162753
            },
            {
                "has_sig": false,
                "upload_time": "2015-11-06T21:07:36",
                "comment_text": "",
                "python_version": "cp32",
                "url": "https://pypi.python.org/packages/20/84/aaaf44c339a3b51196b8b1d0928899cbc02e1583ec455b6777011fdb63b0/psycopg2-2.6.1-cp32-none-win32.whl",
                "md5_digest": "c8a704a73f0ea6369ea74a5a24e8f8db",
                "downloads": 610,
                "filename": "psycopg2-2.6.1-cp32-none-win32.whl",
                "packagetype": "bdist_wheel",
                "path": "20/84/aaaf44c339a3b51196b8b1d0928899cbc02e1583ec455b6777011fdb63b0/psycopg2-2.6.1-cp32-none-win32.whl",
                "size": 815145
            },
            {
                "has_sig": false,
                "upload_time": "2015-11-06T21:07:44",
                "comment_text": "",
                "python_version": "cp32",
                "url": "https://pypi.python.org/packages/84/50/ff71daf3e32a8bff56ac661eff9226d035abaf45fe1af007cfb2134970b3/psycopg2-2.6.1-cp32-none-win_amd64.whl",
                "md5_digest": "e29046e7095483ecacac9e3390318254",
                "downloads": 620,
                "filename": "psycopg2-2.6.1-cp32-none-win_amd64.whl",
                "packagetype": "bdist_wheel",
                "path": "84/50/ff71daf3e32a8bff56ac661eff9226d035abaf45fe1af007cfb2134970b3/psycopg2-2.6.1-cp32-none-win_amd64.whl",
                "size": 1163315
            },
            {
                "has_sig": false,
                "upload_time": "2015-11-06T19:48:39",
                "comment_text": "",
                "python_version": "cp33",
                "url": "https://pypi.python.org/packages/2c/5a/8334a55459289cf8d7485a42bcb2dbe0dab5162973ef66a96baee5107593/psycopg2-2.6.1-cp33-none-win32.whl",
                "md5_digest": "f438d2c01fbaa8f9d0cb150154448a9f",
                "downloads": 769,
                "filename": "psycopg2-2.6.1-cp33-none-win32.whl",
                "packagetype": "bdist_wheel",
                "path": "2c/5a/8334a55459289cf8d7485a42bcb2dbe0dab5162973ef66a96baee5107593/psycopg2-2.6.1-cp33-none-win32.whl",
                "size": 818485
            },
            {
                "has_sig": false,
                "upload_time": "2015-11-06T19:48:52",
                "comment_text": "",
                "python_version": "cp33",
                "url": "https://pypi.python.org/packages/7b/ed/82f31122dcc502d8f43c208a74eaa2b9ff39421aaab1ff8d61547639a474/psycopg2-2.6.1-cp33-none-win_amd64.whl",
                "md5_digest": "632ab3d538a8239b619d434c5e17baf5",
                "downloads": 875,
                "filename": "psycopg2-2.6.1-cp33-none-win_amd64.whl",
                "packagetype": "bdist_wheel",
                "path": "7b/ed/82f31122dcc502d8f43c208a74eaa2b9ff39421aaab1ff8d61547639a474/psycopg2-2.6.1-cp33-none-win_amd64.whl",
                "size": 1160268
            },
            {
                "has_sig": false,
                "upload_time": "2015-11-06T19:49:07",
                "comment_text": "",
                "python_version": "cp34",
                "url": "https://pypi.python.org/packages/f0/34/894f8f486196fdb15d376f77a0102b25628ec0ac71538ed019b3ea93b907/psycopg2-2.6.1-cp34-none-win32.whl",
                "md5_digest": "9d90c554f68cfabed7fdb90107e9d464",
                "downloads": 2628,
                "filename": "psycopg2-2.6.1-cp34-none-win32.whl",
                "packagetype": "bdist_wheel",
                "path": "f0/34/894f8f486196fdb15d376f77a0102b25628ec0ac71538ed019b3ea93b907/psycopg2-2.6.1-cp34-none-win32.whl",
                "size": 818452
            },
            {
                "has_sig": false,
                "upload_time": "2015-11-06T19:49:19",
                "comment_text": "",
                "python_version": "cp34",
                "url": "https://pypi.python.org/packages/b7/90/23af1a90f06dfa012a4ae829821b3161344a9e447358841779d027f14bd7/psycopg2-2.6.1-cp34-none-win_amd64.whl",
                "md5_digest": "4c95328c20e00efc66f0046823f6d1d0",
                "downloads": 3142,
                "filename": "psycopg2-2.6.1-cp34-none-win_amd64.whl",
                "packagetype": "bdist_wheel",
                "path": "b7/90/23af1a90f06dfa012a4ae829821b3161344a9e447358841779d027f14bd7/psycopg2-2.6.1-cp34-none-win_amd64.whl",
                "size": 1160261
            },
            {
                "has_sig": true,
                "upload_time": "2015-06-15T09:50:35",
                "comment_text": "",
                "python_version": "source",
                "url": "https://pypi.python.org/packages/86/fd/cc8315be63a41fe000cce20482a917e874cdc1151e62cb0141f5e55f711e/psycopg2-2.6.1.tar.gz",
                "md5_digest": "842b44f8c95517ed5b792081a2370da1",
                "downloads": 3521176,
                "filename": "psycopg2-2.6.1.tar.gz",
                "packagetype": "sdist",
                "path": "86/fd/cc8315be63a41fe000cce20482a917e874cdc1151e62cb0141f5e55f711e/psycopg2-2.6.1.tar.gz",
                "size": 371373
            }
        ],
        "2.6.2": [
            {
                "has_sig": false,
                "upload_time": "2016-07-08T03:12:31",
                "comment_text": "",
                "python_version": "cp26",
                "url": "https://pypi.python.org/packages/49/fe/edd5a96ece520bf6522e27360f0aa66305e8cafa177c3bf5d5418a6b0741/psycopg2-2.6.2-cp26-none-win32.whl",
                "md5_digest": "24ece1e5ea08083289e564b2b864a5a6",
                "downloads": 465,
                "filename": "psycopg2-2.6.2-cp26-none-win32.whl",
                "packagetype": "bdist_wheel",
                "path": "49/fe/edd5a96ece520bf6522e27360f0aa66305e8cafa177c3bf5d5418a6b0741/psycopg2-2.6.2-cp26-none-win32.whl",
                "size": 807955
            },
            {
                "has_sig": false,
                "upload_time": "2016-07-08T03:12:41",
                "comment_text": "",
                "python_version": "cp26",
                "url": "https://pypi.python.org/packages/14/04/c449c231d35b1d26ebd902aea4f9237da744cd3a0bd9ff89caf616a6e6fc/psycopg2-2.6.2-cp26-none-win_amd64.whl",
                "md5_digest": "3ee8bcfeefb573b7a68000bd25f73f43",
                "downloads": 568,
                "filename": "psycopg2-2.6.2-cp26-none-win_amd64.whl",
                "packagetype": "bdist_wheel",
                "path": "14/04/c449c231d35b1d26ebd902aea4f9237da744cd3a0bd9ff89caf616a6e6fc/psycopg2-2.6.2-cp26-none-win_amd64.whl",
                "size": 1157090
            },
            {
                "has_sig": false,
                "upload_time": "2016-07-08T03:12:48",
                "comment_text": "",
                "python_version": "cp27",
                "url": "https://pypi.python.org/packages/30/b9/629418a0fdc84506cfb9005ac066bb409b40661d2bfde6fc083d93237b27/psycopg2-2.6.2-cp27-none-win32.whl",
                "md5_digest": "be33931d712a47275c3f4a373059f7ea",
                "downloads": 4658,
                "filename": "psycopg2-2.6.2-cp27-none-win32.whl",
                "packagetype": "bdist_wheel",
                "path": "30/b9/629418a0fdc84506cfb9005ac066bb409b40661d2bfde6fc083d93237b27/psycopg2-2.6.2-cp27-none-win32.whl",
                "size": 807955
            },
            {
                "has_sig": false,
                "upload_time": "2016-07-08T03:12:57",
                "comment_text": "",
                "python_version": "cp27",
                "url": "https://pypi.python.org/packages/a4/0e/29d29dceca6e465804ae612bc711a4741599ac849cf0a99acdbf53838581/psycopg2-2.6.2-cp27-none-win_amd64.whl",
                "md5_digest": "08d618f1c5a4db211481e59102cc16f8",
                "downloads": 4240,
                "filename": "psycopg2-2.6.2-cp27-none-win_amd64.whl",
                "packagetype": "bdist_wheel",
                "path": "a4/0e/29d29dceca6e465804ae612bc711a4741599ac849cf0a99acdbf53838581/psycopg2-2.6.2-cp27-none-win_amd64.whl",
                "size": 1157086
            },
            {
                "has_sig": false,
                "upload_time": "2016-07-08T03:13:07",
                "comment_text": "",
                "python_version": "cp32",
                "url": "https://pypi.python.org/packages/ba/29/bb6c465a38f6ba070ad4f4b17797ccc345dcd2cd42eb2f262aa75d86fa52/psycopg2-2.6.2-cp32-none-win32.whl",
                "md5_digest": "0e9dca689b2395dea2498b3b82923b37",
                "downloads": 333,
                "filename": "psycopg2-2.6.2-cp32-none-win32.whl",
                "packagetype": "bdist_wheel",
                "path": "ba/29/bb6c465a38f6ba070ad4f4b17797ccc345dcd2cd42eb2f262aa75d86fa52/psycopg2-2.6.2-cp32-none-win32.whl",
                "size": 808593
            },
            {
                "has_sig": false,
                "upload_time": "2016-07-08T03:13:16",
                "comment_text": "",
                "python_version": "cp32",
                "url": "https://pypi.python.org/packages/d3/bd/f989a3be8cd9fa696471ca399c005c903c3a4b840c419784fb27c0c62ae8/psycopg2-2.6.2-cp32-none-win_amd64.whl",
                "md5_digest": "66243f1c0a3f0365489d84d0e9111e63",
                "downloads": 339,
                "filename": "psycopg2-2.6.2-cp32-none-win_amd64.whl",
                "packagetype": "bdist_wheel",
                "path": "d3/bd/f989a3be8cd9fa696471ca399c005c903c3a4b840c419784fb27c0c62ae8/psycopg2-2.6.2-cp32-none-win_amd64.whl",
                "size": 1158092
            },
            {
                "has_sig": false,
                "upload_time": "2016-07-08T03:11:48",
                "comment_text": "",
                "python_version": "cp33",
                "url": "https://pypi.python.org/packages/6c/b4/d5bf17145954a3c8e80e3601d8eaf486f058ae09688910f1f0a22cb6b1d2/psycopg2-2.6.2-cp33-none-win32.whl",
                "md5_digest": "7d7dbd8e6203e2e757b46d77fcb30eee",
                "downloads": 358,
                "filename": "psycopg2-2.6.2-cp33-none-win32.whl",
                "packagetype": "bdist_wheel",
                "path": "6c/b4/d5bf17145954a3c8e80e3601d8eaf486f058ae09688910f1f0a22cb6b1d2/psycopg2-2.6.2-cp33-none-win32.whl",
                "size": 812530
            },
            {
                "has_sig": false,
                "upload_time": "2016-07-08T03:11:56",
                "comment_text": "",
                "python_version": "cp33",
                "url": "https://pypi.python.org/packages/2a/34/849e0491130bf2f67d72826ad64cfe8d9dc4e322b42ba99ab77dd96d970f/psycopg2-2.6.2-cp33-none-win_amd64.whl",
                "md5_digest": "60816e4ffadd258f3bd1b5c3da62ecfe",
                "downloads": 366,
                "filename": "psycopg2-2.6.2-cp33-none-win_amd64.whl",
                "packagetype": "bdist_wheel",
                "path": "2a/34/849e0491130bf2f67d72826ad64cfe8d9dc4e322b42ba99ab77dd96d970f/psycopg2-2.6.2-cp33-none-win_amd64.whl",
                "size": 1154446
            },
            {
                "has_sig": false,
                "upload_time": "2016-07-08T03:12:04",
                "comment_text": "",
                "python_version": "cp34",
                "url": "https://pypi.python.org/packages/8f/80/20bdb48cfccaf31be57f7ae4b5165d7bb669cfaae5a42eaf00d55b2bf39b/psycopg2-2.6.2-cp34-none-win32.whl",
                "md5_digest": "819bcec9a26fb1877090cf60faf5bfc4",
                "downloads": 1040,
                "filename": "psycopg2-2.6.2-cp34-none-win32.whl",
                "packagetype": "bdist_wheel",
                "path": "8f/80/20bdb48cfccaf31be57f7ae4b5165d7bb669cfaae5a42eaf00d55b2bf39b/psycopg2-2.6.2-cp34-none-win32.whl",
                "size": 812387
            },
            {
                "has_sig": false,
                "upload_time": "2016-07-08T03:12:13",
                "comment_text": "",
                "python_version": "cp34",
                "url": "https://pypi.python.org/packages/fe/23/c67030ab4a43655d10b62acc658829054a97a147819a81094b1e9673e592/psycopg2-2.6.2-cp34-none-win_amd64.whl",
                "md5_digest": "26ca03d4f4f65c75a530824981a60df6",
                "downloads": 1204,
                "filename": "psycopg2-2.6.2-cp34-none-win_amd64.whl",
                "packagetype": "bdist_wheel",
                "path": "fe/23/c67030ab4a43655d10b62acc658829054a97a147819a81094b1e9673e592/psycopg2-2.6.2-cp34-none-win_amd64.whl",
                "size": 1154539
            },
            {
                "has_sig": false,
                "upload_time": "2016-07-08T03:13:21",
                "comment_text": "",
                "python_version": "cp35",
                "url": "https://pypi.python.org/packages/85/bb/7ab5d5b040d6c8a26180acb864f50c1887f27e02e9fb4e94f1f730a4e01b/psycopg2-2.6.2-cp35-none-win32.whl",
                "md5_digest": "9355dc0c57491e4e42bc610428570994",
                "downloads": 2932,
                "filename": "psycopg2-2.6.2-cp35-none-win32.whl",
                "packagetype": "bdist_wheel",
                "path": "85/bb/7ab5d5b040d6c8a26180acb864f50c1887f27e02e9fb4e94f1f730a4e01b/psycopg2-2.6.2-cp35-none-win32.whl",
                "size": 801274
            },
            {
                "has_sig": false,
                "upload_time": "2016-07-08T03:13:26",
                "comment_text": "",
                "python_version": "cp35",
                "url": "https://pypi.python.org/packages/5e/45/de485228f46a2487da8e774fa2dbd772e7e03e65a3c31a322a224806e734/psycopg2-2.6.2-cp35-none-win_amd64.whl",
                "md5_digest": "c8101dfc2a2c2e6eb7e2054c8c0208b2",
                "downloads": 3340,
                "filename": "psycopg2-2.6.2-cp35-none-win_amd64.whl",
                "packagetype": "bdist_wheel",
                "path": "5e/45/de485228f46a2487da8e774fa2dbd772e7e03e65a3c31a322a224806e734/psycopg2-2.6.2-cp35-none-win_amd64.whl",
                "size": 1159852
            },
            {
                "has_sig": false,
                "upload_time": "2016-12-23T16:50:51",
                "comment_text": "",
                "python_version": "cp36",
                "url": "https://pypi.python.org/packages/66/97/e8922a18a142195cfdbdfc9ec84a8d1a46b09edae24a150d79ea90e6b55b/psycopg2-2.6.2-cp36-cp36m-win32.whl",
                "md5_digest": "be2016ebc0a83ef40d068baa25ee4f3f",
                "downloads": 493,
                "filename": "psycopg2-2.6.2-cp36-cp36m-win32.whl",
                "packagetype": "bdist_wheel",
                "path": "66/97/e8922a18a142195cfdbdfc9ec84a8d1a46b09edae24a150d79ea90e6b55b/psycopg2-2.6.2-cp36-cp36m-win32.whl",
                "size": 802352
            },
            {
                "has_sig": false,
                "upload_time": "2016-12-23T16:50:54",
                "comment_text": "",
                "python_version": "cp36",
                "url": "https://pypi.python.org/packages/b6/cb/b7ad5008df09b8392942db9a262435bda778457be4aaba5fc79ead1444b4/psycopg2-2.6.2-cp36-cp36m-win_amd64.whl",
                "md5_digest": "a1cc2cbb0d9a9191c64640d5129402c3",
                "downloads": 582,
                "filename": "psycopg2-2.6.2-cp36-cp36m-win_amd64.whl",
                "packagetype": "bdist_wheel",
                "path": "b6/cb/b7ad5008df09b8392942db9a262435bda778457be4aaba5fc79ead1444b4/psycopg2-2.6.2-cp36-cp36m-win_amd64.whl",
                "size": 1162079
            },
            {
                "has_sig": true,
                "upload_time": "2016-07-07T02:23:58",
                "comment_text": "",
                "python_version": "source",
                "url": "https://pypi.python.org/packages/7b/a8/dc2d50a6f37c157459cd18bab381c8e6134b9381b50fbe969997b2ae7dbc/psycopg2-2.6.2.tar.gz",
                "md5_digest": "4a392949ba31a378a18ed3e775a4693f",
                "downloads": 1545062,
                "filename": "psycopg2-2.6.2.tar.gz",
                "packagetype": "sdist",
                "path": "7b/a8/dc2d50a6f37c157459cd18bab381c8e6134b9381b50fbe969997b2ae7dbc/psycopg2-2.6.2.tar.gz",
                "size": 376348
            }
        ],
        "2.0.14": [
            {
                "has_sig": false,
                "upload_time": "2010-10-19T15:29:17",
                "comment_text": "",
                "python_version": "source",
                "url": "https://pypi.python.org/packages/e0/1c/f0843f50a69fba3db880e9b267d36f6709bbf31a36fc46b82f75e8975ede/psycopg2-2.0.14.tar.gz",
                "md5_digest": "30136c7753acc9cbdc36cc5c2448fdee",
                "downloads": 19521,
                "filename": "psycopg2-2.0.14.tar.gz",
                "packagetype": "sdist",
                "path": "e0/1c/f0843f50a69fba3db880e9b267d36f6709bbf31a36fc46b82f75e8975ede/psycopg2-2.0.14.tar.gz",
                "size": 491362
            }
        ],
        "2.0.13": [
            {
                "has_sig": false,
                "upload_time": "2010-10-19T15:31:38",
                "comment_text": "",
                "python_version": "source",
                "url": "https://pypi.python.org/packages/3a/7a/968afcb86b1958ae963a3aaa42c561e3ed2c2d4a8b773622b03856a16248/psycopg2-2.0.13.tar.gz",
                "md5_digest": "f520260595f4fcf035d26cfd57a75f19",
                "downloads": 14083,
                "filename": "psycopg2-2.0.13.tar.gz",
                "packagetype": "sdist",
                "path": "3a/7a/968afcb86b1958ae963a3aaa42c561e3ed2c2d4a8b773622b03856a16248/psycopg2-2.0.13.tar.gz",
                "size": 258399
            }
        ],
        "2.0.12": [
            {
                "has_sig": false,
                "upload_time": "2010-10-19T15:33:16",
                "comment_text": "",
                "python_version": "source",
                "url": "https://pypi.python.org/packages/6a/8d/ee5c330823d527a5cd14c833063f825211d7b5de6e4897f72e250c107d85/psycopg2-2.0.12.tar.gz",
                "md5_digest": "5c8080d0d0568479f041bb8534caf1f8",
                "downloads": 4001,
                "filename": "psycopg2-2.0.12.tar.gz",
                "packagetype": "sdist",
                "path": "6a/8d/ee5c330823d527a5cd14c833063f825211d7b5de6e4897f72e250c107d85/psycopg2-2.0.12.tar.gz",
                "size": 256169
            }
        ],
        "2.0.11": [
            {
                "has_sig": false,
                "upload_time": "2010-10-19T15:35:04",
                "comment_text": "",
                "python_version": "source",
                "url": "https://pypi.python.org/packages/2d/d7/496da11d7c81971870ddd36800419c4f84e8f6208aac5eabedf9f7748729/psycopg2-2.0.11.tar.gz",
                "md5_digest": "eec2a45bcea75a00cbf20a15ab1b8bae",
                "downloads": 4052,
                "filename": "psycopg2-2.0.11.tar.gz",
                "packagetype": "sdist",
                "path": "2d/d7/496da11d7c81971870ddd36800419c4f84e8f6208aac5eabedf9f7748729/psycopg2-2.0.11.tar.gz",
                "size": 255260
            }
        ],
        "2.0.10": [
            {
                "has_sig": false,
                "upload_time": "2010-10-19T15:36:38",
                "comment_text": "",
                "python_version": "source",
                "url": "https://pypi.python.org/packages/19/79/35c7596bab4456f3610c12ec542a94d51c6781ced587d1d85127210b879b/psycopg2-2.0.10.tar.gz",
                "md5_digest": "2dc60d0fd90ad681e1e9106edef34e97",
                "downloads": 5027,
                "filename": "psycopg2-2.0.10.tar.gz",
                "packagetype": "sdist",
                "path": "19/79/35c7596bab4456f3610c12ec542a94d51c6781ced587d1d85127210b879b/psycopg2-2.0.10.tar.gz",
                "size": 255995
            }
        ]
    },
    "urls": [
        {
            "has_sig": false,
            "upload_time": "2016-07-08T03:12:31",
            "comment_text": "",
            "python_version": "cp26",
            "url": "https://pypi.python.org/packages/49/fe/edd5a96ece520bf6522e27360f0aa66305e8cafa177c3bf5d5418a6b0741/psycopg2-2.6.2-cp26-none-win32.whl",
            "md5_digest": "24ece1e5ea08083289e564b2b864a5a6",
            "downloads": 465,
            "filename": "psycopg2-2.6.2-cp26-none-win32.whl",
            "packagetype": "bdist_wheel",
            "path": "49/fe/edd5a96ece520bf6522e27360f0aa66305e8cafa177c3bf5d5418a6b0741/psycopg2-2.6.2-cp26-none-win32.whl",
            "size": 807955
        },
        {
            "has_sig": false,
            "upload_time": "2016-07-08T03:12:41",
            "comment_text": "",
            "python_version": "cp26",
            "url": "https://pypi.python.org/packages/14/04/c449c231d35b1d26ebd902aea4f9237da744cd3a0bd9ff89caf616a6e6fc/psycopg2-2.6.2-cp26-none-win_amd64.whl",
            "md5_digest": "3ee8bcfeefb573b7a68000bd25f73f43",
            "downloads": 568,
            "filename": "psycopg2-2.6.2-cp26-none-win_amd64.whl",
            "packagetype": "bdist_wheel",
            "path": "14/04/c449c231d35b1d26ebd902aea4f9237da744cd3a0bd9ff89caf616a6e6fc/psycopg2-2.6.2-cp26-none-win_amd64.whl",
            "size": 1157090
        },
        {
            "has_sig": false,
            "upload_time": "2016-07-08T03:12:48",
            "comment_text": "",
            "python_version": "cp27",
            "url": "https://pypi.python.org/packages/30/b9/629418a0fdc84506cfb9005ac066bb409b40661d2bfde6fc083d93237b27/psycopg2-2.6.2-cp27-none-win32.whl",
            "md5_digest": "be33931d712a47275c3f4a373059f7ea",
            "downloads": 4658,
            "filename": "psycopg2-2.6.2-cp27-none-win32.whl",
            "packagetype": "bdist_wheel",
            "path": "30/b9/629418a0fdc84506cfb9005ac066bb409b40661d2bfde6fc083d93237b27/psycopg2-2.6.2-cp27-none-win32.whl",
            "size": 807955
        },
        {
            "has_sig": false,
            "upload_time": "2016-07-08T03:12:57",
            "comment_text": "",
            "python_version": "cp27",
            "url": "https://pypi.python.org/packages/a4/0e/29d29dceca6e465804ae612bc711a4741599ac849cf0a99acdbf53838581/psycopg2-2.6.2-cp27-none-win_amd64.whl",
            "md5_digest": "08d618f1c5a4db211481e59102cc16f8",
            "downloads": 4240,
            "filename": "psycopg2-2.6.2-cp27-none-win_amd64.whl",
            "packagetype": "bdist_wheel",
            "path": "a4/0e/29d29dceca6e465804ae612bc711a4741599ac849cf0a99acdbf53838581/psycopg2-2.6.2-cp27-none-win_amd64.whl",
            "size": 1157086
        },
        {
            "has_sig": false,
            "upload_time": "2016-07-08T03:13:07",
            "comment_text": "",
            "python_version": "cp32",
            "url": "https://pypi.python.org/packages/ba/29/bb6c465a38f6ba070ad4f4b17797ccc345dcd2cd42eb2f262aa75d86fa52/psycopg2-2.6.2-cp32-none-win32.whl",
            "md5_digest": "0e9dca689b2395dea2498b3b82923b37",
            "downloads": 333,
            "filename": "psycopg2-2.6.2-cp32-none-win32.whl",
            "packagetype": "bdist_wheel",
            "path": "ba/29/bb6c465a38f6ba070ad4f4b17797ccc345dcd2cd42eb2f262aa75d86fa52/psycopg2-2.6.2-cp32-none-win32.whl",
            "size": 808593
        },
        {
            "has_sig": false,
            "upload_time": "2016-07-08T03:13:16",
            "comment_text": "",
            "python_version": "cp32",
            "url": "https://pypi.python.org/packages/d3/bd/f989a3be8cd9fa696471ca399c005c903c3a4b840c419784fb27c0c62ae8/psycopg2-2.6.2-cp32-none-win_amd64.whl",
            "md5_digest": "66243f1c0a3f0365489d84d0e9111e63",
            "downloads": 339,
            "filename": "psycopg2-2.6.2-cp32-none-win_amd64.whl",
            "packagetype": "bdist_wheel",
            "path": "d3/bd/f989a3be8cd9fa696471ca399c005c903c3a4b840c419784fb27c0c62ae8/psycopg2-2.6.2-cp32-none-win_amd64.whl",
            "size": 1158092
        },
        {
            "has_sig": false,
            "upload_time": "2016-07-08T03:11:48",
            "comment_text": "",
            "python_version": "cp33",
            "url": "https://pypi.python.org/packages/6c/b4/d5bf17145954a3c8e80e3601d8eaf486f058ae09688910f1f0a22cb6b1d2/psycopg2-2.6.2-cp33-none-win32.whl",
            "md5_digest": "7d7dbd8e6203e2e757b46d77fcb30eee",
            "downloads": 358,
            "filename": "psycopg2-2.6.2-cp33-none-win32.whl",
            "packagetype": "bdist_wheel",
            "path": "6c/b4/d5bf17145954a3c8e80e3601d8eaf486f058ae09688910f1f0a22cb6b1d2/psycopg2-2.6.2-cp33-none-win32.whl",
            "size": 812530
        },
        {
            "has_sig": false,
            "upload_time": "2016-07-08T03:11:56",
            "comment_text": "",
            "python_version": "cp33",
            "url": "https://pypi.python.org/packages/2a/34/849e0491130bf2f67d72826ad64cfe8d9dc4e322b42ba99ab77dd96d970f/psycopg2-2.6.2-cp33-none-win_amd64.whl",
            "md5_digest": "60816e4ffadd258f3bd1b5c3da62ecfe",
            "downloads": 366,
            "filename": "psycopg2-2.6.2-cp33-none-win_amd64.whl",
            "packagetype": "bdist_wheel",
            "path": "2a/34/849e0491130bf2f67d72826ad64cfe8d9dc4e322b42ba99ab77dd96d970f/psycopg2-2.6.2-cp33-none-win_amd64.whl",
            "size": 1154446
        },
        {
            "has_sig": false,
            "upload_time": "2016-07-08T03:12:04",
            "comment_text": "",
            "python_version": "cp34",
            "url": "https://pypi.python.org/packages/8f/80/20bdb48cfccaf31be57f7ae4b5165d7bb669cfaae5a42eaf00d55b2bf39b/psycopg2-2.6.2-cp34-none-win32.whl",
            "md5_digest": "819bcec9a26fb1877090cf60faf5bfc4",
            "downloads": 1040,
            "filename": "psycopg2-2.6.2-cp34-none-win32.whl",
            "packagetype": "bdist_wheel",
            "path": "8f/80/20bdb48cfccaf31be57f7ae4b5165d7bb669cfaae5a42eaf00d55b2bf39b/psycopg2-2.6.2-cp34-none-win32.whl",
            "size": 812387
        },
        {
            "has_sig": false,
            "upload_time": "2016-07-08T03:12:13",
            "comment_text": "",
            "python_version": "cp34",
            "url": "https://pypi.python.org/packages/fe/23/c67030ab4a43655d10b62acc658829054a97a147819a81094b1e9673e592/psycopg2-2.6.2-cp34-none-win_amd64.whl",
            "md5_digest": "26ca03d4f4f65c75a530824981a60df6",
            "downloads": 1204,
            "filename": "psycopg2-2.6.2-cp34-none-win_amd64.whl",
            "packagetype": "bdist_wheel",
            "path": "fe/23/c67030ab4a43655d10b62acc658829054a97a147819a81094b1e9673e592/psycopg2-2.6.2-cp34-none-win_amd64.whl",
            "size": 1154539
        },
        {
            "has_sig": false,
            "upload_time": "2016-07-08T03:13:21",
            "comment_text": "",
            "python_version": "cp35",
            "url": "https://pypi.python.org/packages/85/bb/7ab5d5b040d6c8a26180acb864f50c1887f27e02e9fb4e94f1f730a4e01b/psycopg2-2.6.2-cp35-none-win32.whl",
            "md5_digest": "9355dc0c57491e4e42bc610428570994",
            "downloads": 2932,
            "filename": "psycopg2-2.6.2-cp35-none-win32.whl",
            "packagetype": "bdist_wheel",
            "path": "85/bb/7ab5d5b040d6c8a26180acb864f50c1887f27e02e9fb4e94f1f730a4e01b/psycopg2-2.6.2-cp35-none-win32.whl",
            "size": 801274
        },
        {
            "has_sig": false,
            "upload_time": "2016-07-08T03:13:26",
            "comment_text": "",
            "python_version": "cp35",
            "url": "https://pypi.python.org/packages/5e/45/de485228f46a2487da8e774fa2dbd772e7e03e65a3c31a322a224806e734/psycopg2-2.6.2-cp35-none-win_amd64.whl",
            "md5_digest": "c8101dfc2a2c2e6eb7e2054c8c0208b2",
            "downloads": 3340,
            "filename": "psycopg2-2.6.2-cp35-none-win_amd64.whl",
            "packagetype": "bdist_wheel",
            "path": "5e/45/de485228f46a2487da8e774fa2dbd772e7e03e65a3c31a322a224806e734/psycopg2-2.6.2-cp35-none-win_amd64.whl",
            "size": 1159852
        },
        {
            "has_sig": false,
            "upload_time": "2016-12-23T16:50:51",
            "comment_text": "",
            "python_version": "cp36",
            "url": "https://pypi.python.org/packages/66/97/e8922a18a142195cfdbdfc9ec84a8d1a46b09edae24a150d79ea90e6b55b/psycopg2-2.6.2-cp36-cp36m-win32.whl",
            "md5_digest": "be2016ebc0a83ef40d068baa25ee4f3f",
            "downloads": 493,
            "filename": "psycopg2-2.6.2-cp36-cp36m-win32.whl",
            "packagetype": "bdist_wheel",
            "path": "66/97/e8922a18a142195cfdbdfc9ec84a8d1a46b09edae24a150d79ea90e6b55b/psycopg2-2.6.2-cp36-cp36m-win32.whl",
            "size": 802352
        },
        {
            "has_sig": false,
            "upload_time": "2016-12-23T16:50:54",
            "comment_text": "",
            "python_version": "cp36",
            "url": "https://pypi.python.org/packages/b6/cb/b7ad5008df09b8392942db9a262435bda778457be4aaba5fc79ead1444b4/psycopg2-2.6.2-cp36-cp36m-win_amd64.whl",
            "md5_digest": "a1cc2cbb0d9a9191c64640d5129402c3",
            "downloads": 582,
            "filename": "psycopg2-2.6.2-cp36-cp36m-win_amd64.whl",
            "packagetype": "bdist_wheel",
            "path": "b6/cb/b7ad5008df09b8392942db9a262435bda778457be4aaba5fc79ead1444b4/psycopg2-2.6.2-cp36-cp36m-win_amd64.whl",
            "size": 1162079
        },
        {
            "has_sig": true,
            "upload_time": "2016-07-07T02:23:58",
            "comment_text": "",
            "python_version": "source",
            "url": "https://pypi.python.org/packages/7b/a8/dc2d50a6f37c157459cd18bab381c8e6134b9381b50fbe969997b2ae7dbc/psycopg2-2.6.2.tar.gz",
            "md5_digest": "4a392949ba31a378a18ed3e775a4693f",
            "downloads": 1545062,
            "filename": "psycopg2-2.6.2.tar.gz",
            "packagetype": "sdist",
            "path": "7b/a8/dc2d50a6f37c157459cd18bab381c8e6134b9381b50fbe969997b2ae7dbc/psycopg2-2.6.2.tar.gz",
            "size": 376348
        }
    ]
}
